bluedac/__init__.py
bluedac/blue_res/__init__.py
bluedac/blue_res/bluedac_apigw.py
bluedac/blue_res/bluedac_dashboard.py
bluedac/blue_res/bluedac_lambda.py
bluedac/dac.py
bluedac/templates/add_tag.yml
bluedac/templates/deploy_production.yml
bluedac/templates/deploy_staging.yml
bluedac/templates/deploy_testing.yml
bluedac/templates/gitflow_pipeline.json
bluedac/templates/launch_e2e_tests.yml
bluedac/templates/launch_integration_tests.yml
bluedac/templates/launch_load_tests.yml
bluedac/templates/launch_unit_tests.yml
bluedac/templates/tbd_pipeline.json
bluedac/tests/e2e/e2e_test.py
bluedac/tests/integration/int_test.py
bluedac/tests/unit/dynamo/test_object_creation_dynamo.py
bluedac/tests/unit/dynamo/test_object_retrieve_dynamo.py
bluedac/tests/unit/lambda/test_lambda_alone.py
bluedac/tests/unit/s3/test_object_creation_bucket.py
bluedac/tests/unit/s3/test_object_retrieve_bucket.py
bluedac/utils/__init__.py
bluedac/utils/build_pipeline.py
bluedac/utils/generate_tests.py
bluedac/utils/init.py
bluedac/utils/save_config.py
bluedac/utils/stack_utils.py
bluedac/utils/test_manager.py
bluedac-1.4.5.dist-info/METADATA
bluedac-1.4.5.dist-info/WHEEL
bluedac-1.4.5.dist-info/entry_points.txt
bluedac-1.4.5.dist-info/RECORD
