Metadata-Version: 2.1
Name: bluedac
Version: 1.4.5
Summary: 
Author: ChristianP01
Requires-Python: >=3.1,<4.0
Classifier: Programming Language :: Python :: 3
Classifier: Programming Language :: Python :: 3.4
Classifier: Programming Language :: Python :: 3.5
Classifier: Programming Language :: Python :: 3.6
Classifier: Programming Language :: Python :: 3.7
Classifier: Programming Language :: Python :: 3.8
Classifier: Programming Language :: Python :: 3.9
Classifier: Programming Language :: Python :: 3.10
Classifier: Programming Language :: Python :: 3.11
Classifier: Programming Language :: Python :: 3.12
Requires-Dist: PyYAML (>=6.0.1,<7.0.0)
Requires-Dist: aws-cdk-lib (>=2.144.0,<3.0.0)
Requires-Dist: inquirer (>=3.2.5,<4.0.0)
Requires-Dist: moto (>=5.0.9,<6.0.0)
Requires-Dist: pytest (>=8.2.2,<9.0.0)
Requires-Dist: pytest-cov (>=5.0.0,<6.0.0)
